{
  "servers": {
    "serena-local": {
      "type": "http",
      "url": "http://127.0.0.1:8765/mcp",
      "env": {
        "SISTEMA_TESIS_ROOT": "${workspaceFolder}",
        "SERENA_MCP_DEBUG_LOG": "${workspaceFolder}/historial interno no público/serena_mcp_debug.log",
        "SISTEMA_TESIS_AGENT_ROLE": "Compatible Host (Assistant)",
        "SISTEMA_TESIS_AGENT_PROVIDER": "Host Provider",
        "SISTEMA_TESIS_AGENT_MODEL_VERSION": "Model Version",
        "SISTEMA_TESIS_AGENT_RUNTIME": "Host Runtime",
        "SISTEMA_TESIS_MCP_HOST_KIND": "vscode"
      }
    },
    "serena-local-py": {
      "type": "stdio",
      "command": "${workspaceFolder}\\.venv\\bin\\python.exe",
      "args": [
        "-u",
        "${workspaceFolder}\\07_scripts\\serena_mcp.py"
      ],
      "cwd": "${workspaceFolder}",
      "env": {
        "SISTEMA_TESIS_ROOT": "${workspaceFolder}",
        "SERENA_MCP_DEBUG_LOG": "${workspaceFolder}/historial interno no público/serena_mcp_debug.log",
        "SISTEMA_TESIS_AGENT_ROLE": "Compatible Host (Assistant)",
        "SISTEMA_TESIS_AGENT_PROVIDER": "Host Provider",
        "SISTEMA_TESIS_AGENT_MODEL_VERSION": "Model Version",
        "SISTEMA_TESIS_AGENT_RUNTIME": "Host Runtime",
        "SISTEMA_TESIS_MCP_HOST_KIND": "vscode"
      }
    }
  }
}
